getblocks/__init__.py
getblocks/__main__.py
getblocks/cli.py
getblocks-2024.5.29.dist-info/LICENSE
getblocks-2024.5.29.dist-info/METADATA
getblocks-2024.5.29.dist-info/WHEEL
getblocks-2024.5.29.dist-info/entry_points.txt
getblocks-2024.5.29.dist-info/top_level.txt
getblocks-2024.5.29.dist-info/RECORD
