Metadata-Version: 2.1
Name: getblocks
Version: 2024.5.29
Summary: Down to the smallest sector detail!
Home-page: https://github.com/4n6ir/getblocks
Author: John Lukach
Author-email: hello@4n6ir.com
License: Apache-2.0
Requires-Python: >=3.8
License-File: LICENSE
Requires-Dist: blake3
Requires-Dist: requests
